{"ContractVersion": "2", "AccountNumber": "005205032", "Agency": "1", "PositionDate": "2024-10-01T00:00:00", "TotalAmmount": "18749713.02", "SummaryAccounts": [{"MarketName": "Conta Corrente", "MarketAbbreviation": "CC", "PositionDate": "2024-10-01T00:00:00", "EndPositionValue": "54965.43", "StartPositionValue": "0.0"}, {"MarketName": "Renda Vari\u00e1vel", "MarketAbbreviation": "RV", "PositionDate": "2024-10-01T00:00:00Z", "EndPositionValue": "3143894.51", "StartPositionValue": "0.0"}, {"MarketName": "Renda Fixa", "MarketAbbreviation": "RF", "PositionDate": "2024-10-01T00:00:00", "EndPositionValue": "6187351.57", "StartPositionValue": "0.0"}, {"MarketName": "Fundos de Investimento", "MarketAbbreviation": "FN", "PositionDate": "2024-10-01T00:00:00Z", "EndPositionValue": "9422685.55", "StartPositionValue": "0.0"}, {"MarketName": "Derivativos", "MarketAbbreviation": "DRV", "PositionDate": "2024-10-01T00:00:00Z", "EndPositionValue": "-59184.04", "StartPositionValue": "0.0"}], "InvestmentFund": [{"ShareValue": "4.4230604", "Fund": {"FundName": "BTG Tesouro Selic FIRFRefDI", "SecurityCode": "3842212", "FundCGECode": "1173358", "FundCNPJCode": "09215250000113", "DatePortfolio": "2024-10-01T00:00:00Z", "ManagerName": "BTG PACTUAL ASSET MANAGEMENT S/A DTVM - RJ", "ManagerCGECode": "3", "FundLiquidity": "0", "BenchMark": "CDI", "EsTipoPortfolio": "0", "TipoCvm": "2"}, "Acquisition": [{"CostPrice": "4.1885968", "IncomeTax": "441.11", "VirtualIOF": "0.0", "NetAssetValue": "56771.40", "GrossAssetValue": "57212.51", "AcquisitionDate": "2024-03-15T00:00:00Z", "NumberOfShares": "12935.051139", "AcquisitionNumber": "1", "OrigemAmortizacao": "false", "CostValue": "54179.71", "CotaCetipada": "false"}, {"CostPrice": "4.3103362", "IncomeTax": "38.34", "VirtualIOF": "0.0", "NetAssetValue": "6648.30", "GrossAssetValue": "6686.64", "AcquisitionDate": "2024-07-01T00:00:00Z", "NumberOfShares": "1511.767484", "AcquisitionNumber": "2", "OrigemAmortizacao": "false", "CostValue": "6516.23", "CotaCetipada": "false"}], "CotaCetipadaFundoExterno": "false", "PositionDate": "2024-10-01T00:00:00Z", "ProcessingDateTime": "2024-10-02T00:36:32.738Z"}, {"ShareValue": "2.929624053718", "Fund": {"FundName": "BTG CDB Plus FIRF CrPr", "SecurityCode": "3842210", "FundCGECode": "1173294", "FundCNPJCode": "27717359000130", "DatePortfolio": "2024-10-01T00:00:00Z", "ManagerName": "BTG PACTUAL ASSET MANAGEMENT S/A DTVM - RJ", "ManagerCGECode": "3", "FundLiquidity": "0", "BenchMark": "CDI", "EsTipoPortfolio": "0", "TipoCvm": "2"}, "Acquisition": [{"CostPrice": "2.904785021508", "IncomeTax": "145.57", "VirtualIOF": "20.01", "NetAssetValue": "78501.40", "GrossAssetValue": "78666.98", "AcquisitionDate": "2024-09-02T00:00:00Z", "NumberOfShares": "26852.24532", "AcquisitionNumber": "1", "OrigemAmortizacao": "false", "CostValue": "78000.00", "CotaCetipada": "false"}], "CotaCetipadaFundoExterno": "false", "PositionDate": "2024-10-01T00:00:00Z", "ProcessingDateTime": "2024-10-02T01:06:19.869Z"}, {"ShareValue": "2.45022228", "Fund": {"FundName": "REAL INVESTOR FICFIM", "SecurityCode": "2332619", "FundCGECode": "856789", "FundCNPJCode": "28911549000157", "DatePortfolio": "2024-10-01T00:00:00Z", "ManagerName": "REAL INVESTOR ASSET MANAGEMENT LTDA", "ManagerCGECode": "557790", "FundLiquidity": "30", "BenchMark": "CDI", "EsTipoPortfolio": "0", "TipoCvm": "4"}, "Acquisition": [{"CostPrice": "2.33070384", "IncomeTax": "1850.09", "VirtualIOF": "0.0", "NetAssetValue": "364334.33", "GrossAssetValue": "366184.42", "AcquisitionDate": "2024-02-26T00:00:00Z", "NumberOfShares": "149449.46970361", "AcquisitionNumber": "1", "OrigemAmortizacao": "false", "CostValue": "348322.45", "CotaCetipada": "false"}, {"CostPrice": "2.38442037", "IncomeTax": "522.0", "VirtualIOF": "0.0", "NetAssetValue": "112439.6", "GrossAssetValue": "112961.6", "AcquisitionDate": "2024-04-29T00:00:00Z", "NumberOfShares": "46102.59389212", "AcquisitionNumber": "2", "OrigemAmortizacao": "false", "CostValue": "109927.96", "CotaCetipada": "false"}, {"CostPrice": "2.44288541", "IncomeTax": "304.09", "VirtualIOF": "0.0", "NetAssetValue": "451047.42", "GrossAssetValue": "451351.51", "AcquisitionDate": "2024-08-13T00:00:00Z", "NumberOfShares": "184208.3947769", "AcquisitionNumber": "3", "OrigemAmortizacao": "false", "CostValue": "450000.00", "CotaCetipada": "false"}], "CotaCetipadaFundoExterno": "false", "PositionDate": "2024-10-01T00:00:00Z", "ProcessingDateTime": "2024-10-02T10:11:47.569Z"}, {"ShareValue": "1615.74454807", "Fund": {"FundName": "APUAMA YARA FICFIM CrPr", "SecurityCode": "9653526", "FundCGECode": "15237854", "FundCNPJCode": "34027976000170", "DatePortfolio": "2024-10-01T00:00:00Z", "ManagerName": "APUAMA CAPITAL GESTORA DE RECURSOS LTDA", "ManagerCGECode": "935007", "FundLiquidity": "35", "BenchMark": "CDI", "EsTipoPortfolio": "0", "TipoCvm": "4"}, "Acquisition": [{"CostPrice": "1610.93742435", "IncomeTax": "104.55", "VirtualIOF": "1256.28", "NetAssetValue": "577068.64", "GrossAssetValue": "578429.47", "AcquisitionDate": "2024-09-23T00:00:00Z", "NumberOfShares": "357.9956188", "AcquisitionNumber": "1", "OrigemAmortizacao": "false", "CostValue": "576708.54", "CotaCetipada": "false"}], "CotaCetipadaFundoExterno": "false", "PositionDate": "2024-10-01T00:00:00Z", "ProcessingDateTime": "2024-10-02T11:35:40.922Z"}, {"ShareValue": "1.5525979", "Fund": {"FundName": "Riza Lotus FIRFRefDI CrPr", "SecurityCode": "2573202", "FundCGECode": "947540", "FundCNPJCode": "36498670000127", "DatePortfolio": "2024-10-01T00:00:00Z", "ManagerName": "RIZA LIQUIDOS GESTORA DE RECURSOS LTDA", "ManagerCGECode": "9385894", "FundLiquidity": "1", "BenchMark": "CDI", "EsTipoPortfolio": "0", "TipoCvm": "2"}, "Acquisition": [{"CostPrice": "1.2423", "IncomeTax": "308.45", "VirtualIOF": "0.0", "NetAssetValue": "30345.26", "GrossAssetValue": "30653.71", "AcquisitionDate": "2022-11-30T00:00:00Z", "NumberOfShares": "19743.495147", "AcquisitionNumber": "1", "OrigemAmortizacao": "false", "CostValue": "24527.34", "CotaCetipada": "false"}, {"CostPrice": "1.2613606", "IncomeTax": "303.79", "VirtualIOF": "0.0", "NetAssetValue": "29886.70", "GrossAssetValue": "30190.49", "AcquisitionDate": "2023-01-17T00:00:00Z", "NumberOfShares": "19445.143963", "AcquisitionNumber": "2", "OrigemAmortizacao": "false", "CostValue": "24527.34", "CotaCetipada": "false"}, {"CostPrice": "1.4264237", "IncomeTax": "3834.1", "VirtualIOF": "0.0", "NetAssetValue": "374689.79", "GrossAssetValue": "378523.89", "AcquisitionDate": "2024-01-22T00:00:00Z", "NumberOfShares": "243800.337019", "AcquisitionNumber": "3", "OrigemAmortizacao": "false", "CostValue": "347762.58", "CotaCetipada": "false"}, {"CostPrice": "1.4359673", "IncomeTax": "1731.23", "VirtualIOF": "0.0", "NetAssetValue": "174599.35", "GrossAssetValue": "176330.58", "AcquisitionDate": "2024-02-06T00:00:00Z", "NumberOfShares": "113571.312972", "AcquisitionNumber": "4", "OrigemAmortizacao": "false", "CostValue": "163084.69", "CotaCetipada": "false"}, {"CostPrice": "1.445035", "IncomeTax": "12895.15", "VirtualIOF": "0.0", "NetAssetValue": "1341193.11", "GrossAssetValue": "1354088.26", "AcquisitionDate": "2024-02-27T00:00:00Z", "NumberOfShares": "872143.5605", "AcquisitionNumber": "5", "OrigemAmortizacao": "false", "CostValue": "1260277.97", "CotaCetipada": "false"}, {"CostPrice": "1.5316034", "IncomeTax": "7.3", "VirtualIOF": "0.0", "NetAssetValue": "2392.47", "GrossAssetValue": "2399.77", "AcquisitionDate": "2024-08-21T00:00:00Z", "NumberOfShares": "1545.648175", "AcquisitionNumber": "6", "OrigemAmortizacao": "false", "CostValue": "2367.32", "CotaCetipada": "false"}], "CotaCetipadaFundoExterno": "false", "PositionDate": "2024-10-01T00:00:00Z", "ProcessingDateTime": "2024-10-02T11:37:13.531Z"}, {"ShareValue": "1.7017193", "Fund": {"FundName": "BTG CRED CORP PLUS FIM CrPr", "SecurityCode": "3851712", "FundCGECode": "1173367", "FundCNPJCode": "33599991000120", "DatePortfolio": "2024-10-01T00:00:00Z", "ManagerName": "BTG PACTUAL ASSET MANAGEMENT S/A DTVM - RJ", "ManagerCGECode": "3", "FundLiquidity": "60", "BenchMark": "CDI", "EsTipoPortfolio": "0", "TipoCvm": "4"}, "Acquisition": [{"CostPrice": "1.5811546", "IncomeTax": "23929.01", "VirtualIOF": "0.0", "NetAssetValue": "2386887.06", "GrossAssetValue": "2410816.07", "AcquisitionDate": "2024-02-23T00:00:00Z", "NumberOfShares": "1416694.322514", "AcquisitionNumber": "1", "OrigemAmortizacao": "false", "CostValue": "2240012.74", "CotaCetipada": "false"}], "CotaCetipadaFundoExterno": "false", "PositionDate": "2024-10-01T00:00:00Z", "ProcessingDateTime": "2024-10-02T11:58:33.571Z"}, {"ShareValue": "57.257467", "Fund": {"FundName": "BTG Hedge FIRF CrPr", "SecurityCode": "5031121", "FundCGECode": "2762127", "FundCNPJCode": "00888897000131", "DatePortfolio": "2024-10-01T00:00:00Z", "ManagerName": "BTG PACTUAL ASSET MANAGEMENT S/A DTVM - RJ", "ManagerCGECode": "3", "FundLiquidity": "1", "BenchMark": "CDI", "EsTipoPortfolio": "0", "TipoCvm": "2"}, "Acquisition": [{"CostPrice": "56.6557768", "IncomeTax": "2604.09", "VirtualIOF": "0.0", "NetAssetValue": "1098762.96", "GrossAssetValue": "1101367.05", "AcquisitionDate": "2024-08-12T00:00:00Z", "NumberOfShares": "19235.343598", "AcquisitionNumber": "6", "OrigemAmortizacao": "false", "CostValue": "1089793.33", "CotaCetipada": "false"}], "CotaCetipadaFundoExterno": "false", "PositionDate": "2024-10-01T00:00:00Z", "ProcessingDateTime": "2024-10-02T13:12:22.351Z"}, {"ShareValue": "20.518973", "Fund": {"FundName": "Sul America Premium FIRFRefDI CrPr", "SecurityCode": "6265911", "FundCGECode": "4358190", "FundCNPJCode": "24325096000126", "DatePortfolio": "2024-10-01T00:00:00Z", "ManagerName": "SUL AMERICA INVESTIMENTOS GESTORA DE RECURSOS S.A.", "ManagerCGECode": "381190", "FundLiquidity": "1", "BenchMark": "CDI", "EsTipoPortfolio": "0", "TipoCvm": "2"}, "Acquisition": [{"CostPrice": "17.5046996", "IncomeTax": "2800.14", "VirtualIOF": "0.0", "NetAssetValue": "308445.87", "GrossAssetValue": "311246.01", "AcquisitionDate": "2023-06-05T00:00:00Z", "NumberOfShares": "15168.6935306", "AcquisitionNumber": "1", "OrigemAmortizacao": "false", "CostValue": "265523.42", "CotaCetipada": "false"}], "CotaCetipadaFundoExterno": "false", "PositionDate": "2024-10-01T00:00:00Z", "ProcessingDateTime": "2024-10-02T14:03:35.042Z"}, {"ShareValue": "1.4928759", "Fund": {"FundName": "LIBRA FICFIM CrPr", "SecurityCode": "5821758", "FundCGECode": "3944472", "FundCNPJCode": "45274408000190", "DatePortfolio": "2024-10-01T00:00:00Z", "ManagerName": "CATALISE INVESTIMENTOS LTDA", "ManagerCGECode": "421701", "FundLiquidity": "46", "BenchMark": "CDI", "EsTipoPortfolio": "0", "TipoCvm": "4"}, "Acquisition": [{"CostPrice": "1.3783591", "IncomeTax": "14033.28", "VirtualIOF": "0.0", "NetAssetValue": "1332840.71", "GrossAssetValue": "1346873.99", "AcquisitionDate": "2024-02-23T00:00:00Z", "NumberOfShares": "902200.90569", "AcquisitionNumber": "1", "OrigemAmortizacao": "false", "CostValue": "1243556.83", "CotaCetipada": "false"}, {"CostPrice": "1.3846888", "IncomeTax": "648.81", "VirtualIOF": "0.0", "NetAssetValue": "62928.62", "GrossAssetValue": "63577.43", "AcquisitionDate": "2024-03-06T00:00:00Z", "NumberOfShares": "42587.217084", "AcquisitionNumber": "2", "OrigemAmortizacao": "false", "CostValue": "58970.04", "CotaCetipada": "false"}, {"CostPrice": "1.4430101", "IncomeTax": "2332.58", "VirtualIOF": "0.0", "NetAssetValue": "308034.46", "GrossAssetValue": "310367.04", "AcquisitionDate": "2024-06-28T00:00:00Z", "NumberOfShares": "207898.752753", "AcquisitionNumber": "3", "OrigemAmortizacao": "false", "CostValue": "300000.00", "CotaCetipada": "false"}, {"CostPrice": "1.4649934", "IncomeTax": "1070.58", "VirtualIOF": "0.0", "NetAssetValue": "253687.55", "GrossAssetValue": "254758.13", "AcquisitionDate": "2024-08-12T00:00:00Z", "NumberOfShares": "170649.232959", "AcquisitionNumber": "4", "OrigemAmortizacao": "false", "CostValue": "250000.00", "CotaCetipada": "false"}], "CotaCetipadaFundoExterno": "false", "PositionDate": "2024-10-01T00:00:00Z", "ProcessingDateTime": "2024-10-02T19:40:03.656Z"}], "FixedIncome": [{"AccountingGroupCode": "LCA", "Issuer": "BANCO BTG PACTUAL S A", "IssueDate": "2024-08-09T00:00:00-03:00", "SecurityCode": "10808943", "IssuerCGECode": "1", "PriceType": "200", "ValueType": "Boleta (Cliente)", "Yield": "0.0", "Ticker": "LCA-24H01343146", "ReferenceIndexName": "CDI", "ReferenceIndexValue": "93% CDI", "IndexYieldRate": "93,00% do CDI", "MaturityDate": "2025-05-09T00:00:00-03:00", "Quantity": "342.0", "Price": "506.834855", "GrossValue": "173337.52", "IncomeTax": "525.94", "IOFTax": "0.0", "NetValue": "172811.58", "IsLiquidity": "false", "Acquisitions": [{"AcquisitionQuantity": "342.0", "SecurityCode": "10808943", "YieldToMaturity": "93.0", "AcquisitionDate": "2024-08-09T00:00:00-03:00", "CostPrice": "500.0", "InitialInvestmentValue": "171000.0", "InitialInvestmentQuantity": "342.0", "NetValue": "172811.58", "GrossValue": "173337.52", "IncomeTax": "525.94", "IOFTax": "0.0", "Yield": "93.0", "ComplementYield": "0.0", "IndexYieldRate": "93,00% do CDI", "TransferId": "180241304", "FTSId": "12593766", "InterfaceDate": "2024-10-01T00:00:00-03:00", "PriceIncomeTax": "1.537842375", "PriceVirtualIOF": "0.0", "DateTimeUpdate": "2024-10-01T05:46:34", "PriceType": "200", "Price": "506.834855", "IsVirtual": "false"}], "FTSId": "0", "IsRepo": "false", "CetipCode": "24H01343146", "TaxFree": "false", "IssuerType": "TituloPrivado", "Default": "false", "YieldAvg": "0.0", "DebtEarlyTerminationSchedules": [{"IndexRateMultiplier": "93.0", "Rate": "0.0", "Type": "NO", "EarlyTerminationPeriod": {"FromDateTime": "2024-08-09T00:00:00-03:00", "ToDateTime": "2025-05-09T00:00:00-03:00"}}]}, {"AccountingGroupCode": "LFT", "Issuer": "BACEN-BANCO CENTRAL DO BRASIL - RJ", "IssueDate": "2022-05-10T00:00:00-03:00", "SecurityCode": "6606975", "IssuerCGECode": "4449", "PriceType": "9", "ValueType": "Mercado Fechamento", "Yield": "0.1", "Ticker": "LFT", "ReferenceIndexName": "SELIC", "ReferenceIndexValue": "100% SELIC", "IndexYieldRate": "SELIC + 0,10%", "MaturityDate": "2029-03-01T00:00:00-03:00", "Quantity": "161.0", "Price": "15323.207824", "GrossValue": "2467036.45", "IncomeTax": "28871.57", "IOFTax": "0.0", "NetValue": "2438164.88", "IsLiquidity": "false", "Acquisitions": [{"AcquisitionQuantity": "161.0", "SecurityCode": "6606975", "YieldToMaturity": "0.1", "AcquisitionDate": "2024-02-23T00:00:00-03:00", "CostPrice": "14426.57498", "InitialInvestmentValue": "2322678.57", "InitialInvestmentQuantity": "161.0", "NetValue": "2438164.88", "GrossValue": "2467036.45", "IncomeTax": "28871.57", "IOFTax": "0.0", "Yield": "100.0", "ComplementYield": "0.1", "IndexYieldRate": "SELIC + 0,10%", "TransferId": "27695930", "FTSId": "0", "InterfaceDate": "2024-10-01T00:00:00-03:00", "PriceIncomeTax": "179.3265688", "PriceVirtualIOF": "0.0", "DateTimeUpdate": "2024-10-01T22:15:41", "PriceType": "9", "Price": "15323.207824", "IsVirtual": "false"}], "FTSId": "0", "IsRepo": "false", "CetipCode": "LFT", "SelicCode": "210100", "ISIN": "BRSTNCLF1RL5", "TaxFree": "false", "IssuerType": "Titulo Publico", "Default": "false", "YieldAvg": "0.1", "DebtEarlyTerminationSchedules": [{"IndexRateMultiplier": "100.0", "Rate": "0.0", "Type": "NO", "EarlyTerminationPeriod": {"FromDateTime": "2022-05-10T00:00:00-03:00", "ToDateTime": "2029-03-01T00:00:00-03:00"}}]}, {"AccountingGroupCode": "LFT", "Issuer": "BACEN-BANCO CENTRAL DO BRASIL - RJ", "IssueDate": "2024-01-10T00:00:00-03:00", "SecurityCode": "9352191", "IssuerCGECode": "4449", "PriceType": "9", "ValueType": "Mercado Fechamento", "Yield": "0.12", "Ticker": "LFT", "ReferenceIndexName": "SELIC", "ReferenceIndexValue": "100% SELIC", "IndexYieldRate": "SELIC + 0,12%", "MaturityDate": "2030-03-01T00:00:00-03:00", "Quantity": "4.0", "Price": "15293.485932", "GrossValue": "61173.94", "IncomeTax": "91.64", "IOFTax": "12.59", "NetValue": "61069.71", "IsLiquidity": "false", "Acquisitions": [{"AcquisitionQuantity": "4.0", "SecurityCode": "9352191", "YieldToMaturity": "0.12", "AcquisitionDate": "2024-09-02T00:00:00-03:00", "CostPrice": "15188.513127", "InitialInvestmentValue": "60754.05", "InitialInvestmentQuantity": "4.0", "NetValue": "61069.71", "GrossValue": "61173.94", "IncomeTax": "91.64", "IOFTax": "12.59", "Yield": "100.0", "ComplementYield": "0.12", "IndexYieldRate": "SELIC + 0,12%", "TransferId": "40084998", "FTSId": "0", "InterfaceDate": "2024-10-01T00:00:00-03:00", "PriceIncomeTax": "22.91031469125", "PriceVirtualIOF": "3.14918415", "DateTimeUpdate": "2024-10-01T22:15:41", "PriceType": "9", "Price": "15293.485932", "IsVirtual": "false"}], "FTSId": "0", "IsRepo": "false", "CetipCode": "LFT", "SelicCode": "210100", "ISIN": "BRSTNCLF1RO9", "TaxFree": "false", "IssuerType": "Titulo Publico", "Default": "false", "YieldAvg": "0.12", "DebtEarlyTerminationSchedules": [{"IndexRateMultiplier": "100.0", "Rate": "0.0", "Type": "NO", "EarlyTerminationPeriod": {"FromDateTime": "2024-01-10T00:00:00-03:00", "ToDateTime": "2030-03-01T00:00:00-03:00"}}]}, {"AccountingGroupCode": "LFT", "Issuer": "BACEN-BANCO CENTRAL DO BRASIL - RJ", "IssueDate": "2024-04-03T00:00:00-03:00", "SecurityCode": "9906104", "IssuerCGECode": "4449", "PriceType": "9", "ValueType": "Mercado Fechamento", "Yield": "0.07", "Ticker": "LFT", "ReferenceIndexName": "SELIC", "ReferenceIndexValue": "100% SELIC", "IndexYieldRate": "SELIC + 0,07%", "MaturityDate": "2030-06-01T00:00:00-03:00", "Quantity": "196.0", "Price": "15285.423406", "GrossValue": "2995942.98", "IncomeTax": "0.0", "IOFTax": "0.0", "NetValue": "2995942.98", "IsLiquidity": "false", "Acquisitions": [{"AcquisitionQuantity": "196.0", "SecurityCode": "9906104", "YieldToMaturity": "0.07", "AcquisitionDate": "2024-09-19T00:00:00-03:00", "CostPrice": "15305.818995", "InitialInvestmentValue": "2999940.52", "InitialInvestmentQuantity": "196.0", "NetValue": "2995942.98", "GrossValue": "2995942.98", "IncomeTax": "0.0", "IOFTax": "0.0", "Yield": "100.0", "ComplementYield": "0.07", "IndexYieldRate": "SELIC + 0,07%", "TransferId": "40173183", "FTSId": "0", "InterfaceDate": "2024-10-01T00:00:00-03:00", "PriceIncomeTax": "0.0", "PriceVirtualIOF": "0.0", "DateTimeUpdate": "2024-10-01T22:15:41", "PriceType": "9", "Price": "15285.423406", "IsVirtual": "false"}], "FTSId": "0", "IsRepo": "false", "CetipCode": "LFT", "SelicCode": "210100", "ISIN": "BRSTNCLF1RQ4", "TaxFree": "false", "IssuerType": "Titulo Publico", "Default": "false", "YieldAvg": "0.07", "DebtEarlyTerminationSchedules": [{"IndexRateMultiplier": "100.0", "Rate": "0.0", "Type": "NO", "EarlyTerminationPeriod": {"FromDateTime": "2024-04-03T00:00:00-03:00", "ToDateTime": "2030-06-01T00:00:00-03:00"}}]}, {"AccountingGroupCode": "LFT", "Issuer": "BACEN-BANCO CENTRAL DO BRASIL - RJ", "IssueDate": "2023-07-05T00:00:00-03:00", "SecurityCode": "8089557", "IssuerCGECode": "4449", "PriceType": "9", "ValueType": "Mercado Fechamento", "Yield": "0.06", "Ticker": "LFT", "ReferenceIndexName": "SELIC", "ReferenceIndexValue": "100% SELIC", "IndexYieldRate": "SELIC + 0,06%", "MaturityDate": "2029-09-01T00:00:00-03:00", "Quantity": "32.0", "Price": "15308.146471", "GrossValue": "489860.68", "IncomeTax": "0.0", "IOFTax": "0.0", "NetValue": "489860.68", "IsLiquidity": "false", "Acquisitions": [{"AcquisitionQuantity": "32.0", "SecurityCode": "8089557", "YieldToMaturity": "0.06", "AcquisitionDate": "2024-09-19T00:00:00-03:00", "CostPrice": "15321.170099", "InitialInvestmentValue": "490277.44", "InitialInvestmentQuantity": "32.0", "NetValue": "489860.68", "GrossValue": "489860.68", "IncomeTax": "0.0", "IOFTax": "0.0", "Yield": "100.0", "ComplementYield": "0.06", "IndexYieldRate": "SELIC + 0,06%", "TransferId": "40173243", "FTSId": "0", "InterfaceDate": "2024-10-01T00:00:00-03:00", "PriceIncomeTax": "0.0", "PriceVirtualIOF": "0.0", "DateTimeUpdate": "2024-10-01T22:15:41", "PriceType": "9", "Price": "15308.146471", "IsVirtual": "false"}], "FTSId": "0", "IsRepo": "false", "CetipCode": "LFT", "SelicCode": "210100", "ISIN": "BRSTNCLF1RM3", "TaxFree": "false", "IssuerType": "Titulo Publico", "Default": "false", "YieldAvg": "0.06", "DebtEarlyTerminationSchedules": [{"IndexRateMultiplier": "100.0", "Rate": "0.0", "Type": "NO", "EarlyTerminationPeriod": {"FromDateTime": "2023-07-05T00:00:00-03:00", "ToDateTime": "2029-09-01T00:00:00-03:00"}}]}], "InvestmentFundCotaCetipada": [], "Credits": [{"Loan": []}], "Equities": [{"StockPositions": [{"Ticker": "IMAB11", "Description": "IT NOW IMA-BF11", "Quantity": "17601.0", "MarketPrice": "99.76", "PrevClose": "99.76", "GrossValue": "1755875.76", "CostPrice": "0.0", "ISINCode": "BRIMABCTF004", "IncomeTax": "0.0", "InitialInvestimentValue": "0.0", "SectorCode": "143", "SectorDescription": "FUNDOS DE A\u00c7\u00d5ES", "SecurityCode": "1885217", "QuantityPendingSettlement": "0.0", "IsFII": "false", "AveragePrice": {"Price": "99.747744", "Adjustable": "false", "Proceeds": "99.747744", "AccumulatedProceeds": "0.0", "TotalProceeds": "0.0"}, "ReferenceAsset": {"SecurityCode": "0"}, "InterfaceDate": "2024-10-01T00:00:00Z", "PreferenceToIncome": "IMAB11", "FirstDealingDate": "2019-05-17T00:00:00Z", "ReferencePrice": "0.0", "QuotingFactor": "1", "IssuerCge": "676904", "EquityTypeDescription": "COTAS"}, {"Ticker": "IRFM11", "Description": "IT NOW IRF-MF11", "Quantity": "16475.0", "MarketPrice": "84.25", "PrevClose": "84.25", "GrossValue": "1388018.75", "CostPrice": "0.0", "ISINCode": "BRIRFMCTF009", "IncomeTax": "0.0", "InitialInvestimentValue": "0.0", "SectorCode": "143", "SectorDescription": "FUNDOS DE A\u00c7\u00d5ES", "SecurityCode": "2072961", "QuantityPendingSettlement": "0.0", "IsFII": "false", "AveragePrice": {"Price": "83.12078", "Adjustable": "false", "Proceeds": "83.12078", "AccumulatedProceeds": "0.0", "TotalProceeds": "0.0"}, "ReferenceAsset": {"SecurityCode": "0"}, "InterfaceDate": "2024-10-01T00:00:00Z", "PreferenceToIncome": "IRFM11", "FirstDealingDate": "2019-09-24T00:00:00Z", "ReferencePrice": "0.0", "QuotingFactor": "1", "IssuerCge": "826073", "EquityTypeDescription": "COTAS"}], "CollateralPositions": [{"CollateralDescription": "COBERTURA CBLC", "Description": "IT NOW IMA-BF11", "MarketPrice": "99.76", "Quantity": "12311.0", "Ticker": "IMAB11", "TotalValue": "1228145.36", "SecurityCode": "1885217"}], "StructuredProducts": [], "PortfolioInvestments": []}], "Derivative": [{"NDFPosition": [{"NDFCode": "1654154", "BuySell": "COMPRA", "MaturityDate": "2024-11-11T00:00:00Z", "CurrentSecurityPrice": "5.6358", "GrossValue": "-5530.72", "InceptionDate": "2024-08-30T00:00:00Z", "ForwardRate": "5.7", "Principal": "26350.0", "CurrentCurrencyPrice": "1.0", "IOFTax": "0.0", "IncomeTax": "0.0", "PriceType": "5", "ReferencedSecurity": "USD", "ValueType": "Mercado Fechamento"}, {"NDFCode": "1660332", "BuySell": "COMPRA", "MaturityDate": "2024-10-31T00:00:00Z", "CurrentSecurityPrice": "5.623", "GrossValue": "-53653.32", "InceptionDate": "2024-09-03T00:00:00Z", "ForwardRate": "5.69", "Principal": "258000.0", "CurrentCurrencyPrice": "1.0", "IOFTax": "0.0", "IncomeTax": "0.0", "PriceType": "5", "ReferencedSecurity": "USD", "ValueType": "Mercado Fechamento"}]}], "PayableReceivables": [{"Credit": []}], "PendingSettlements": [{"FixedIncome": [], "InvestmentFund": [], "Equities": []}], "Cash": [{"CashCollateral": [], "CurrentAccount": {"Value": "54965.43", "PositionDate": "2024-10-01T00:00:00"}, "CashInvested": []}], "EventCreateDate": "2024-10-09T15:42:50.599"}