{"ContractVersion": "2", "AccountNumber": "005205032", "Agency": "1", "PositionDate": "2024-05-31T00:00:00", "TotalAmmount": "17277179.72", "SummaryAccounts": [{"MarketName": "Conta Corrente", "MarketAbbreviation": "CC", "PositionDate": "2024-05-31T00:00:00", "EndPositionValue": "55071.02", "StartPositionValue": "0.0"}, {"MarketName": "Renda Vari\u00e1vel", "MarketAbbreviation": "RV", "PositionDate": "2024-05-31T00:00:00Z", "EndPositionValue": "1446481.61", "StartPositionValue": "0.0"}, {"MarketName": "Renda Fixa", "MarketAbbreviation": "RF", "PositionDate": "2024-05-31T00:00:00", "EndPositionValue": "3872545.91", "StartPositionValue": "0.0"}, {"MarketName": "Fundos de Investimento", "MarketAbbreviation": "FN", "PositionDate": "2024-05-31T00:00:00Z", "EndPositionValue": "11899113.20", "StartPositionValue": "0.0"}, {"MarketName": "Derivativos", "MarketAbbreviation": "DRV", "PositionDate": "2024-05-31T00:00:00Z", "EndPositionValue": "3967.98", "StartPositionValue": "0.0"}], "InvestmentFund": [{"ShareValue": "4.2755997", "Fund": {"FundName": "BTG Tesouro Selic FIRFRefDI", "SecurityCode": "3842212", "FundCGECode": "1173358", "FundCNPJCode": "09215250000113", "DatePortfolio": "2024-05-31T00:00:00Z", "ManagerName": "BTG PACTUAL ASSET MANAGEMENT S/A DTVM - RJ", "ManagerCGECode": "3", "FundLiquidity": "0", "EsTipoPortfolio": "0", "TipoCvm": "2"}, "Acquisition": [{"CostPrice": "4.1885968", "IncomeTax": "261.48", "VirtualIOF": "0.0", "NetAssetValue": "164361.26", "GrossAssetValue": "164622.74", "AcquisitionDate": "2024-03-15T00:00:00Z", "NumberOfShares": "38502.84115", "AcquisitionNumber": "1", "OrigemAmortizacao": "false", "CostValue": "161272.88", "CotaCetipada": "false"}], "CotaCetipadaFundoExterno": "false", "PositionDate": "2024-05-31T00:00:00Z", "ProcessingDateTime": "2024-05-31T01:11:31.023Z"}, {"ShareValue": "19.7821399", "Fund": {"FundName": "Sul America Premium FIRFRefDI CrPr", "SecurityCode": "6265911", "FundCGECode": "4358190", "FundCNPJCode": "24325096000126", "DatePortfolio": "2024-05-31T00:00:00Z", "ManagerName": "SUL AMERICA INVESTIMENTOS GESTORA DE RECURSOS S.A.", "ManagerCGECode": "381190", "FundLiquidity": "1", "EsTipoPortfolio": "0", "TipoCvm": "2"}, "Acquisition": [{"CostPrice": "17.5046996", "IncomeTax": "844.2", "VirtualIOF": "0.0", "NetAssetValue": "299225.02", "GrossAssetValue": "300069.22", "AcquisitionDate": "2023-06-05T00:00:00Z", "NumberOfShares": "15168.6935306", "AcquisitionNumber": "1", "OrigemAmortizacao": "false", "CostValue": "265523.42", "CotaCetipada": "false"}], "CotaCetipadaFundoExterno": "false", "PositionDate": "2024-05-31T00:00:00Z", "ProcessingDateTime": "2024-06-01T08:16:28.383Z"}, {"ShareValue": "1.6294912", "Fund": {"FundName": "BTG CRED CORP PLUS FIM CrPr", "SecurityCode": "3851712", "FundCGECode": "1173367", "FundCNPJCode": "33599991000120", "DatePortfolio": "2024-05-31T00:00:00Z", "ManagerName": "BTG PACTUAL ASSET MANAGEMENT S/A DTVM - RJ", "ManagerCGECode": "3", "FundLiquidity": "60", "BenchMark": "CDI", "EsTipoPortfolio": "2", "TipoCvm": "4"}, "Acquisition": [{"CostPrice": "1.5811546", "IncomeTax": "5183.55", "VirtualIOF": "0.0", "NetAssetValue": "2303307.38", "GrossAssetValue": "2308490.93", "AcquisitionDate": "2024-02-23T00:00:00Z", "NumberOfShares": "1416694.322514", "AcquisitionNumber": "1", "OrigemAmortizacao": "false", "CostValue": "2240012.74", "CotaCetipada": "false"}], "CotaCetipadaFundoExterno": "false", "PositionDate": "2024-05-31T00:00:00Z", "ProcessingDateTime": "2024-06-03T11:46:00.871Z"}, {"ShareValue": "2.40827544", "Fund": {"FundName": "REAL INVESTOR FIC FIM", "SecurityCode": "2332619", "FundCGECode": "856789", "FundCNPJCode": "28911549000157", "DatePortfolio": "2024-05-31T00:00:00Z", "ManagerName": "REAL INVESTOR GESTAO DE RECURSOS LTDA", "ManagerCGECode": "557790", "FundLiquidity": "30", "BenchMark": "CDI", "EsTipoPortfolio": "2", "TipoCvm": "4"}, "Acquisition": [{"CostPrice": "2.33070384", "IncomeTax": "887.52", "VirtualIOF": "0.0", "NetAssetValue": "359027.97", "GrossAssetValue": "359915.49", "AcquisitionDate": "2024-02-26T00:00:00Z", "NumberOfShares": "149449.46970361", "AcquisitionNumber": "1", "OrigemAmortizacao": "false", "CostValue": "348322.45", "CotaCetipada": "false"}, {"CostPrice": "2.38442037", "IncomeTax": "86.88", "VirtualIOF": "0.0", "NetAssetValue": "110940.86", "GrossAssetValue": "111027.74", "AcquisitionDate": "2024-04-29T00:00:00Z", "NumberOfShares": "46102.59389212", "AcquisitionNumber": "2", "OrigemAmortizacao": "false", "CostValue": "109927.96", "CotaCetipada": "false"}], "CotaCetipadaFundoExterno": "false", "PositionDate": "2024-05-31T00:00:00Z", "ProcessingDateTime": "2024-06-03T11:46:26.868Z"}, {"ShareValue": "55.2365614", "Fund": {"FundName": "BTG Hedge FIRF CrPr", "SecurityCode": "5031121", "FundCGECode": "2762127", "FundCNPJCode": "00888897000131", "DatePortfolio": "2024-05-31T00:00:00Z", "ManagerName": "BTG PACTUAL ASSET MANAGEMENT S/A DTVM - RJ", "ManagerCGECode": "3", "FundLiquidity": "1", "BenchMark": "CDI", "EsTipoPortfolio": "1", "TipoCvm": "2"}, "Acquisition": [{"CostPrice": "50.9364159", "IncomeTax": "339.58", "VirtualIOF": "0.0", "NetAssetValue": "84642.10", "GrossAssetValue": "84981.68", "AcquisitionDate": "2023-08-29T00:00:00Z", "NumberOfShares": "1538.504241", "AcquisitionNumber": "1", "OrigemAmortizacao": "false", "CostValue": "78365.89", "CotaCetipada": "false"}, {"CostPrice": "51.0120347", "IncomeTax": "1777.14", "VirtualIOF": "0.0", "NetAssetValue": "450899.03", "GrossAssetValue": "452676.17", "AcquisitionDate": "2023-09-04T00:00:00Z", "NumberOfShares": "8195.227136", "AcquisitionNumber": "2", "OrigemAmortizacao": "false", "CostValue": "418055.21", "CotaCetipada": "false"}, {"CostPrice": "52.7995938", "IncomeTax": "9548.08", "VirtualIOF": "0.0", "NetAssetValue": "2804349.45", "GrossAssetValue": "2813897.53", "AcquisitionDate": "2023-12-21T00:00:00Z", "NumberOfShares": "50942.663004", "AcquisitionNumber": "3", "OrigemAmortizacao": "false", "CostValue": "2689751.91", "CotaCetipada": "false"}, {"CostPrice": "53.2413365", "IncomeTax": "4312.67", "VirtualIOF": "0.0", "NetAssetValue": "1543565.59", "GrossAssetValue": "1547878.26", "AcquisitionDate": "2024-01-16T00:00:00Z", "NumberOfShares": "28022.712214", "AcquisitionNumber": "4", "OrigemAmortizacao": "false", "CostValue": "1491966.65", "CotaCetipada": "false"}, {"CostPrice": "53.345766", "IncomeTax": "1361.35", "VirtualIOF": "0.0", "NetAssetValue": "513734.86", "GrossAssetValue": "515096.21", "AcquisitionDate": "2024-01-22T00:00:00Z", "NumberOfShares": "9325.276458", "AcquisitionNumber": "5", "OrigemAmortizacao": "false", "CostValue": "497464.02", "CotaCetipada": "false"}], "CotaCetipadaFundoExterno": "false", "PositionDate": "2024-05-31T00:00:00Z", "ProcessingDateTime": "2024-06-03T12:18:49.952Z"}, {"ShareValue": "1.4906031", "Fund": {"FundName": "Riza Lotus FIRFRefDI CrPr", "SecurityCode": "2573202", "FundCGECode": "947540", "FundCNPJCode": "36498670000127", "DatePortfolio": "2024-05-31T00:00:00Z", "ManagerName": "RIZA LIQUIDOS GESTORA DE RECURSOS LTDA", "ManagerCGECode": "9385894", "FundLiquidity": "1", "BenchMark": "CDI", "EsTipoPortfolio": "2", "TipoCvm": "2"}, "Acquisition": [{"CostPrice": "1.2423", "IncomeTax": "94.25", "VirtualIOF": "0.0", "NetAssetValue": "29335.47", "GrossAssetValue": "29429.72", "AcquisitionDate": "2022-11-30T00:00:00Z", "NumberOfShares": "19743.495147", "AcquisitionNumber": "1", "OrigemAmortizacao": "false", "CostValue": "24527.34", "CotaCetipada": "false"}, {"CostPrice": "1.2613606", "IncomeTax": "92.83", "VirtualIOF": "0.0", "NetAssetValue": "28892.16", "GrossAssetValue": "28984.99", "AcquisitionDate": "2023-01-17T00:00:00Z", "NumberOfShares": "19445.143963", "AcquisitionNumber": "2", "OrigemAmortizacao": "false", "CostValue": "24527.34", "CotaCetipada": "false"}, {"CostPrice": "1.4264237", "IncomeTax": "1204.89", "VirtualIOF": "0.0", "NetAssetValue": "362204.65", "GrossAssetValue": "363409.54", "AcquisitionDate": "2024-01-22T00:00:00Z", "NumberOfShares": "243800.337019", "AcquisitionNumber": "3", "OrigemAmortizacao": "false", "CostValue": "347762.58", "CotaCetipada": "false"}, {"CostPrice": "1.4359673", "IncomeTax": "479.02", "VirtualIOF": "0.0", "NetAssetValue": "168810.73", "GrossAssetValue": "169289.75", "AcquisitionDate": "2024-02-06T00:00:00Z", "NumberOfShares": "113571.312972", "AcquisitionNumber": "4", "OrigemAmortizacao": "false", "CostValue": "163084.69", "CotaCetipada": "false"}, {"CostPrice": "1.445035", "IncomeTax": "3079.48", "VirtualIOF": "0.0", "NetAssetValue": "1296940.41", "GrossAssetValue": "1300019.89", "AcquisitionDate": "2024-02-27T00:00:00Z", "NumberOfShares": "872143.5605", "AcquisitionNumber": "5", "OrigemAmortizacao": "false", "CostValue": "1260277.97", "CotaCetipada": "false"}], "CotaCetipadaFundoExterno": "false", "PositionDate": "2024-05-31T00:00:00Z", "ProcessingDateTime": "2024-06-03T13:44:46.997Z"}, {"ShareValue": "1.4281756", "Fund": {"FundName": "LIBRA FC FIM CP", "SecurityCode": "5821758", "FundCGECode": "3944472", "FundCNPJCode": "45274408000190", "DatePortfolio": "2024-05-31T00:00:00Z", "ManagerName": "CATALISE INVESTIMENTOS LTDA", "ManagerCGECode": "421701", "FundLiquidity": "46", "BenchMark": "CDI", "EsTipoPortfolio": "20", "TipoCvm": "4"}, "Acquisition": [{"CostPrice": "1.3783591", "IncomeTax": "3488.09", "VirtualIOF": "0.0", "NetAssetValue": "1285013.23", "GrossAssetValue": "1288501.32", "AcquisitionDate": "2024-02-23T00:00:00Z", "NumberOfShares": "902200.90569", "AcquisitionNumber": "1", "OrigemAmortizacao": "false", "CostValue": "1243556.83", "CotaCetipada": "false"}, {"CostPrice": "1.3846888", "IncomeTax": "144.24", "VirtualIOF": "0.0", "NetAssetValue": "60677.78", "GrossAssetValue": "60822.02", "AcquisitionDate": "2024-03-06T00:00:00Z", "NumberOfShares": "42587.217084", "AcquisitionNumber": "2", "OrigemAmortizacao": "false", "CostValue": "58970.04", "CotaCetipada": "false"}], "CotaCetipadaFundoExterno": "false", "PositionDate": "2024-05-31T00:00:00Z", "ProcessingDateTime": "2024-06-04T11:21:26.42Z"}], "FixedIncome": [{"AccountingGroupCode": "CDB", "Issuer": "BANCO BTG PACTUAL S A", "IssueDate": "2024-02-27T00:00:00-03:00", "SecurityCode": "9660534", "IssuerCGECode": "1", "PriceType": "200", "ValueType": "Boleta (Cliente)", "Yield": "0.0", "Ticker": "CDB-CDB224BMSOQ", "ReferenceIndexName": "CDI", "ReferenceIndexValue": "102.85% CDI", "IndexYieldRate": "102,85% do CDI", "MaturityDate": "2024-08-27T00:00:00-03:00", "Quantity": "125000000.0", "Price": "0.0102739", "GrossValue": "1284237.5", "IncomeTax": "7703.43", "IOFTax": "0.0", "NetValue": "1276534.07", "IsLiquidity": "false", "Acquisitions": [{"AcquisitionQuantity": "125000000.0", "SecurityCode": "9660534", "YieldToMaturity": "102.85", "AcquisitionDate": "2024-02-27T00:00:00-03:00", "CostPrice": "0.01", "InitialInvestmentValue": "1250000.0", "InitialInvestmentQuantity": "125000000.0", "NetValue": "1276534.07", "GrossValue": "1284237.5", "IncomeTax": "7703.43", "IOFTax": "0.0", "Yield": "102.85", "ComplementYield": "0.0", "IndexYieldRate": "102,85% do CDI", "TransferId": "142306062", "FTSId": "10049210", "InterfaceDate": "2024-05-31T00:00:00-03:00", "PriceIncomeTax": "0.0000616275", "PriceVirtualIOF": "0.0", "DateTimeUpdate": "2024-05-31T02:44:53", "PriceType": "200", "Price": "0.0102739", "IsVirtual": "false"}], "FTSId": "0", "IsRepo": "false", "CetipCode": "CDB224BMSOQ", "TaxFree": "false", "IssuerType": "Titulo Privado", "Default": "false", "YieldAvg": "0.0", "DebtEarlyTerminationSchedules": [{"IndexRateMultiplier": "102.85", "Rate": "0.0", "Type": "NO", "EarlyTerminationPeriod": {"FromDateTime": "2024-02-27T00:00:00-03:00", "ToDateTime": "2024-06-26T00:00:00-03:00"}}, {"IndexRateMultiplier": "102.85", "Rate": "0.0", "Type": "YES", "EarlyTerminationPeriod": {"FromDateTime": "2024-06-26T00:00:00-03:00", "ToDateTime": "2024-08-27T00:00:00-03:00"}}]}, {"AccountingGroupCode": "LFT", "Issuer": "BACEN-BANCO CENTRAL DO BRASIL - RJ", "IssueDate": "2022-05-10T00:00:00-03:00", "SecurityCode": "6606975", "IssuerCGECode": "4449", "PriceType": "9", "ValueType": "Mercado Fechamento", "Yield": "0.1", "Ticker": "LFT", "ReferenceIndexName": "SELIC", "ReferenceIndexValue": "100% SELIC", "IndexYieldRate": "SELIC + 0,10%", "MaturityDate": "2029-03-01T00:00:00-03:00", "Quantity": "175.0", "Price": "14790.33382", "GrossValue": "2588308.41", "IncomeTax": "14323.0", "IOFTax": "0.0", "NetValue": "2573985.41", "IsLiquidity": "false", "Acquisitions": [{"AcquisitionQuantity": "175.0", "SecurityCode": "6606975", "YieldToMaturity": "0.1", "AcquisitionDate": "2024-02-23T00:00:00-03:00", "CostPrice": "14426.57498", "InitialInvestmentValue": "2524650.62", "InitialInvestmentQuantity": "175.0", "NetValue": "2573985.41", "GrossValue": "2588308.41", "IncomeTax": "14323.0", "IOFTax": "0.0", "Yield": "100.0", "ComplementYield": "0.1", "IndexYieldRate": "SELIC + 0,10%", "TransferId": "27695930", "FTSId": "0", "InterfaceDate": "2024-05-31T00:00:00-03:00", "PriceIncomeTax": "81.845739", "PriceVirtualIOF": "0.0", "DateTimeUpdate": "2024-05-31T23:10:27", "PriceType": "9", "Price": "14790.33382", "IsVirtual": "false"}], "FTSId": "0", "IsRepo": "false", "CetipCode": "LFT", "SelicCode": "210100", "ISIN": "BRSTNCLF1RL5", "TaxFree": "false", "IssuerType": "Titulo Publico", "Default": "false", "YieldAvg": "0.1", "DebtEarlyTerminationSchedules": [{"IndexRateMultiplier": "100.0", "Rate": "0.0", "Type": "NO", "EarlyTerminationPeriod": {"FromDateTime": "2022-05-10T00:00:00-03:00", "ToDateTime": "2029-03-01T00:00:00-03:00"}}]}], "InvestmentFundCotaCetipada": [], "Credits": [{"Loan": []}], "Equities": [{"StockPositions": [{"Ticker": "IMAB11", "Description": "IT NOW IMA-BF11", "Quantity": "7711.0", "MarketPrice": "98.62", "PrevClose": "98.62", "GrossValue": "760458.82", "CostPrice": "0.0", "ISINCode": "BRIMABCTF004", "IncomeTax": "0.0", "InitialInvestimentValue": "0.0", "SectorCode": "143", "SectorDescription": "FUNDOS DE A\u00c7\u00d5ES", "SecurityCode": "1885217", "QuantityPendingSettlement": "0.0", "IsFII": "false", "AveragePrice": {"Price": "98.500209", "Adjustable": "false", "Proceeds": "98.500209", "AccumulatedProceeds": "0.0", "TotalProceeds": "0.0"}, "ReferenceAsset": {"SecurityCode": "0"}, "InterfaceDate": "2024-05-31T00:00:00Z", "PreferenceToIncome": "IMAB11", "FirstDealingDate": "2019-05-17T00:00:00Z", "ReferencePrice": "0.0", "QuotingFactor": "1", "IssuerCge": "676904", "EquityTypeDescription": "COTAS"}, {"Ticker": "IRFM11", "Description": "IT NOW IRF-MF11", "Quantity": "9080.0", "MarketPrice": "82.61", "PrevClose": "82.61", "GrossValue": "750098.80", "CostPrice": "0.0", "ISINCode": "BRIRFMCTF009", "IncomeTax": "0.0", "InitialInvestimentValue": "0.0", "SectorCode": "143", "SectorDescription": "FUNDOS DE A\u00c7\u00d5ES", "SecurityCode": "2072961", "QuantityPendingSettlement": "0.0", "IsFII": "false", "AveragePrice": {"Price": "81.806059", "Adjustable": "false", "Proceeds": "81.806059", "AccumulatedProceeds": "0.0", "TotalProceeds": "0.0"}, "ReferenceAsset": {"SecurityCode": "0"}, "InterfaceDate": "2024-05-31T00:00:00Z", "PreferenceToIncome": "IRFM11", "FirstDealingDate": "2019-09-24T00:00:00Z", "ReferencePrice": "0.0", "QuotingFactor": "1", "IssuerCge": "826073", "EquityTypeDescription": "COTAS"}], "CollateralPositions": [], "StructuredProducts": [{"Code": "6944370", "Name": "Venda de Put", "ReferenceSecurityCode": "0", "ReferenceProductSymbol": "PTAX", "FixingDate": "2024-06-28T00:00:00Z", "Quantity": "258000.0", "GrossValue": "-64076.0050787050716000"}], "PortfolioInvestments": []}], "Derivative": [{"NDFPosition": [{"NDFCode": "1494436", "BuySell": "COMPRA", "MaturityDate": "2024-08-26T00:00:00Z", "CurrentSecurityPrice": "5.1184", "GrossValue": "3967.98", "InceptionDate": "2024-05-03T00:00:00Z", "ForwardRate": "5.135", "Principal": "26350.4", "CurrentCurrencyPrice": "1.0", "IOFTax": "0.0", "IncomeTax": "0.0", "PriceType": "5", "ReferencedSecurity": "USD", "ValueType": "Mercado Fechamento"}], "CetipOptionPosition": []}], "PayableReceivables": [{"Credit": []}], "PendingSettlements": [{"FixedIncome": [], "InvestmentFund": [], "Equities": []}], "Cash": [{"CashCollateral": [], "CurrentAccount": {"Value": "55071.02", "PositionDate": "2024-05-31T00:00:00"}, "CashInvested": []}], "EventCreateDate": "2024-10-09T15:41:24.694"}