{"ContractVersion": "2", "AccountNumber": "005205032", "Agency": "1", "PositionDate": "2024-02-05T00:00:00", "TotalAmmount": "9554809.31", "SummaryAccounts": [{"MarketName": "Conta Corrente", "MarketAbbreviation": "CC", "PositionDate": "2024-01-31T00:00:00", "EndPositionValue": "163975.45", "StartPositionValue": "0.0"}, {"MarketName": "Fundos de Investimento", "MarketAbbreviation": "FN", "PositionDate": "2024-02-05T00:00:00Z", "EndPositionValue": "9390833.86", "StartPositionValue": "0.0"}], "InvestmentFund": [{"ShareValue": "1.4341203", "Fund": {"FundName": "RIZA LOTUS FIRF DI", "SecurityCode": "2573202", "FundCGECode": "947540", "FundCNPJCode": "36498670000127", "DatePortfolio": "2024-02-05T00:00:00Z", "ManagerName": "RIZA GESTORA DE RECURSOS LTDA", "ManagerCGECode": "848718", "FundLiquidity": "1", "BenchMark": "CDI", "EsTipoPortfolio": "2", "TipoCvm": "2"}, "Acquisition": [{"CostPrice": "1.2423", "IncomeTax": "161.07", "VirtualIOF": "0.0", "NetAssetValue": "28407.18", "GrossAssetValue": "28568.25", "AcquisitionDate": "2022-11-30T00:00:00Z", "NumberOfShares": "19920.403406", "AcquisitionNumber": "1", "OrigemAmortizacao": "false", "CostValue": "24747.12", "CotaCetipada": "false"}, {"CostPrice": "1.2613606", "IncomeTax": "158.64", "VirtualIOF": "0.0", "NetAssetValue": "27977.91", "GrossAssetValue": "28136.55", "AcquisitionDate": "2023-01-17T00:00:00Z", "NumberOfShares": "19619.382162", "AcquisitionNumber": "2", "OrigemAmortizacao": "false", "CostValue": "24747.12", "CotaCetipada": "false"}, {"CostPrice": "1.4264237", "IncomeTax": "199.71", "VirtualIOF": "1000.91", "NetAssetValue": "350687.89", "GrossAssetValue": "351888.51", "AcquisitionDate": "2024-01-22T00:00:00Z", "NumberOfShares": "245368.890043", "AcquisitionNumber": "3", "OrigemAmortizacao": "false", "CostValue": "350000.00", "CotaCetipada": "false"}], "CotaCetipadaFundoExterno": "false", "PositionDate": "2024-02-05T00:00:00Z", "ProcessingDateTime": "2024-02-06T10:56:13.403Z"}, {"ShareValue": "1.2075671", "Fund": {"FundName": "UJAY CASH FIM", "SecurityCode": "6529691", "FundCGECode": "4610459", "FundCNPJCode": "47032680000199", "DatePortfolio": "2024-02-05T00:00:00Z", "ManagerName": "UJAY CAPITAL INVESTIMENTOS LTDA.", "ManagerCGECode": "289327", "FundLiquidity": "1", "BenchMark": "CDI", "EsTipoPortfolio": "2", "TipoCvm": "4"}, "Acquisition": [{"CostPrice": "1.1911841", "IncomeTax": "8378.49", "VirtualIOF": "0.0", "NetAssetValue": "2736359.22", "GrossAssetValue": "2744737.71", "AcquisitionDate": "2023-12-21T00:00:00Z", "NumberOfShares": "2272948.404869", "AcquisitionNumber": "1", "OrigemAmortizacao": "false", "CostValue": "2707500.00", "CotaCetipada": "false"}, {"CostPrice": "1.2028035", "IncomeTax": "254.85", "VirtualIOF": "1441.59", "NetAssetValue": "650877.83", "GrossAssetValue": "652574.27", "AcquisitionDate": "2024-01-23T00:00:00Z", "NumberOfShares": "540404.147477", "AcquisitionNumber": "2", "OrigemAmortizacao": "false", "CostValue": "650000.00", "CotaCetipada": "false"}], "CotaCetipadaFundoExterno": "false", "PositionDate": "2024-02-05T00:00:00Z", "ProcessingDateTime": "2024-02-06T11:33:31.518Z"}, {"ShareValue": "53.6599636", "Fund": {"FundName": "BTG HEDGE FIRF CrPr", "SecurityCode": "5031121", "FundCGECode": "2762127", "FundCNPJCode": "00888897000131", "DatePortfolio": "2024-02-05T00:00:00Z", "ManagerName": "BTG PACTUAL ASSET MANAGEMENT S/A DTVM - RJ", "ManagerCGECode": "3", "FundLiquidity": "1", "BenchMark": "CDI", "EsTipoPortfolio": "1", "TipoCvm": "2"}, "Acquisition": [{"CostPrice": "50.9364159", "IncomeTax": "628.25", "VirtualIOF": "0.0", "NetAssetValue": "82580.21", "GrossAssetValue": "83208.46", "AcquisitionDate": "2023-08-29T00:00:00Z", "NumberOfShares": "1550.661949", "AcquisitionNumber": "1", "OrigemAmortizacao": "false", "CostValue": "78985.16", "CotaCetipada": "false"}, {"CostPrice": "51.0120347", "IncomeTax": "3298.94", "VirtualIOF": "0.0", "NetAssetValue": "439931.73", "GrossAssetValue": "443230.67", "AcquisitionDate": "2023-09-04T00:00:00Z", "NumberOfShares": "8259.988227", "AcquisitionNumber": "2", "OrigemAmortizacao": "false", "CostValue": "421358.81", "CotaCetipada": "false"}, {"CostPrice": "52.7995938", "IncomeTax": "9926.72", "VirtualIOF": "0.0", "NetAssetValue": "2741692.01", "GrossAssetValue": "2751618.73", "AcquisitionDate": "2023-12-21T00:00:00Z", "NumberOfShares": "51278.803588", "AcquisitionNumber": "3", "OrigemAmortizacao": "false", "CostValue": "2707500.00", "CotaCetipada": "false"}, {"CostPrice": "53.2413365", "IncomeTax": "1777.98", "VirtualIOF": "3892.1", "NetAssetValue": "1506124.15", "GrossAssetValue": "1511794.23", "AcquisitionDate": "2024-01-16T00:00:00Z", "NumberOfShares": "28173.597783", "AcquisitionNumber": "4", "OrigemAmortizacao": "false", "CostValue": "1500000.00", "CotaCetipada": "false"}, {"CostPrice": "53.345766", "IncomeTax": "311.42", "VirtualIOF": "1560.81", "NetAssetValue": "501072.69", "GrossAssetValue": "502944.92", "AcquisitionDate": "2024-01-22T00:00:00Z", "NumberOfShares": "9372.81508", "AcquisitionNumber": "5", "OrigemAmortizacao": "false", "CostValue": "500000.00", "CotaCetipada": "false"}], "CotaCetipadaFundoExterno": "false", "PositionDate": "2024-02-05T00:00:00Z", "ProcessingDateTime": "2024-02-06T12:11:12.931Z"}, {"ShareValue": "19.1012253", "Fund": {"FundName": "SUL AMERICA PREMIUM FIRF REF DI CrPr", "SecurityCode": "6265911", "FundCGECode": "4358190", "FundCNPJCode": "24325096000126", "DatePortfolio": "2024-02-05T00:00:00Z", "ManagerName": "SUL AMERICA INVESTIMENTOS GESTORA DE RECURSOS S.A.", "ManagerCGECode": "381190", "FundLiquidity": "1", "BenchMark": "CDI", "EsTipoPortfolio": "2", "TipoCvm": "2"}, "Acquisition": [{"CostPrice": "17.5046996", "IncomeTax": "2063.83", "VirtualIOF": "0.0", "NetAssetValue": "290067.73", "GrossAssetValue": "292131.56", "AcquisitionDate": "2023-06-05T00:00:00Z", "NumberOfShares": "15293.8650243", "AcquisitionNumber": "1", "OrigemAmortizacao": "false", "CostValue": "267714.51", "CotaCetipada": "false"}], "CotaCetipadaFundoExterno": "false", "PositionDate": "2024-02-05T00:00:00Z", "ProcessingDateTime": "2024-02-07T17:13:42.367Z"}], "InvestmentFundCotaCetipada": [], "Derivative": [{}], "PayableReceivables": [{"Credit": []}], "PendingSettlements": [{"InvestmentFund": []}], "Cash": [{"CashCollateral": [], "CurrentAccount": {"Value": "163975.45", "PositionDate": "2024-01-31T00:00:00"}, "CashInvested": []}], "EventCreateDate": "2024-10-09T15:39:57.787"}