{"ContractVersion": "2", "AccountNumber": "005205032", "Agency": "1", "PositionDate": "2024-02-20T00:00:00", "TotalAmmount": "9600800.28", "SummaryAccounts": [{"MarketName": "Conta Corrente", "MarketAbbreviation": "CC", "PositionDate": "2024-02-07T00:00:00", "EndPositionValue": "0.0", "StartPositionValue": "0.0"}, {"MarketName": "Fundos de Investimento", "MarketAbbreviation": "FN", "PositionDate": "2024-02-20T00:00:00Z", "EndPositionValue": "9600800.28", "StartPositionValue": "0.0"}], "InvestmentFund": [{"ShareValue": "1.4415484", "Fund": {"FundName": "RIZA LOTUS FIRF DI", "SecurityCode": "2573202", "FundCGECode": "947540", "FundCNPJCode": "36498670000127", "DatePortfolio": "2024-02-20T00:00:00Z", "ManagerName": "RIZA GESTORA DE RECURSOS LTDA", "ManagerCGECode": "848718", "FundLiquidity": "1", "BenchMark": "CDI", "EsTipoPortfolio": "2", "TipoCvm": "2"}, "Acquisition": [{"CostPrice": "1.2423", "IncomeTax": "186.97", "VirtualIOF": "0.0", "NetAssetValue": "28529.26", "GrossAssetValue": "28716.23", "AcquisitionDate": "2022-11-30T00:00:00Z", "NumberOfShares": "19920.403406", "AcquisitionNumber": "1", "OrigemAmortizacao": "false", "CostValue": "24747.12", "CotaCetipada": "false"}, {"CostPrice": "1.2613606", "IncomeTax": "184.14", "VirtualIOF": "0.0", "NetAssetValue": "28098.15", "GrossAssetValue": "28282.29", "AcquisitionDate": "2023-01-17T00:00:00Z", "NumberOfShares": "19619.382162", "AcquisitionNumber": "2", "OrigemAmortizacao": "false", "CostValue": "24747.12", "CotaCetipada": "false"}, {"CostPrice": "1.4264237", "IncomeTax": "809.95", "VirtualIOF": "111.33", "NetAssetValue": "352789.85", "GrossAssetValue": "353711.13", "AcquisitionDate": "2024-01-22T00:00:00Z", "NumberOfShares": "245368.890043", "AcquisitionNumber": "3", "OrigemAmortizacao": "false", "CostValue": "350000.00", "CotaCetipada": "false"}, {"CostPrice": "1.4359673", "IncomeTax": "67.4", "VirtualIOF": "337.78", "NetAssetValue": "164207.58", "GrossAssetValue": "164612.76", "AcquisitionDate": "2024-02-06T00:00:00Z", "NumberOfShares": "114191.632358", "AcquisitionNumber": "4", "OrigemAmortizacao": "false", "CostValue": "163975.45", "CotaCetipada": "false"}], "CotaCetipadaFundoExterno": "false", "PositionDate": "2024-02-20T00:00:00Z", "ProcessingDateTime": "2024-02-21T10:33:19.991Z"}, {"ShareValue": "1.2121895", "Fund": {"FundName": "UJAY CASH FIM", "SecurityCode": "6529691", "FundCGECode": "4610459", "FundCNPJCode": "47032680000199", "DatePortfolio": "2024-02-20T00:00:00Z", "ManagerName": "UJAY CAPITAL INVESTIMENTOS LTDA.", "ManagerCGECode": "289327", "FundLiquidity": "1", "BenchMark": "CDI", "EsTipoPortfolio": "2", "TipoCvm": "4"}, "Acquisition": [{"CostPrice": "1.1911841", "IncomeTax": "10742.44", "VirtualIOF": "0.0", "NetAssetValue": "2744501.75", "GrossAssetValue": "2755244.19", "AcquisitionDate": "2023-12-21T00:00:00Z", "NumberOfShares": "2272948.404869", "AcquisitionNumber": "1", "OrigemAmortizacao": "false", "CostValue": "2707500.00", "CotaCetipada": "false"}, {"CostPrice": "1.2028035", "IncomeTax": "1072.78", "VirtualIOF": "304.33", "NetAssetValue": "653695.12", "GrossAssetValue": "655072.23", "AcquisitionDate": "2024-01-23T00:00:00Z", "NumberOfShares": "540404.147477", "AcquisitionNumber": "2", "OrigemAmortizacao": "false", "CostValue": "650000.00", "CotaCetipada": "false"}], "CotaCetipadaFundoExterno": "false", "PositionDate": "2024-02-20T00:00:00Z", "ProcessingDateTime": "2024-02-21T11:28:03.063Z"}, {"ShareValue": "19.1851693", "Fund": {"FundName": "SUL AMERICA PREMIUM FIRF REF DI CrPr", "SecurityCode": "6265911", "FundCGECode": "4358190", "FundCNPJCode": "24325096000126", "DatePortfolio": "2024-02-20T00:00:00Z", "ManagerName": "SUL AMERICA INVESTIMENTOS GESTORA DE RECURSOS S.A.", "ManagerCGECode": "381190", "FundLiquidity": "1", "BenchMark": "CDI", "EsTipoPortfolio": "2", "TipoCvm": "2"}, "Acquisition": [{"CostPrice": "17.5046996", "IncomeTax": "2320.59", "VirtualIOF": "0.0", "NetAssetValue": "291094.80", "GrossAssetValue": "293415.39", "AcquisitionDate": "2023-06-05T00:00:00Z", "NumberOfShares": "15293.8650243", "AcquisitionNumber": "1", "OrigemAmortizacao": "false", "CostValue": "267714.51", "CotaCetipada": "false"}], "CotaCetipadaFundoExterno": "false", "PositionDate": "2024-02-20T00:00:00Z", "ProcessingDateTime": "2024-02-21T11:33:27.698Z"}, {"ShareValue": "53.9534577", "Fund": {"FundName": "BTG HEDGE FIRF CrPr", "SecurityCode": "5031121", "FundCGECode": "2762127", "FundCNPJCode": "00888897000131", "DatePortfolio": "2024-02-20T00:00:00Z", "ManagerName": "BTG PACTUAL ASSET MANAGEMENT S/A DTVM - RJ", "ManagerCGECode": "3", "FundLiquidity": "1", "BenchMark": "CDI", "EsTipoPortfolio": "1", "TipoCvm": "2"}, "Acquisition": [{"CostPrice": "50.9364159", "IncomeTax": "730.65", "VirtualIOF": "0.0", "NetAssetValue": "82932.92", "GrossAssetValue": "83663.57", "AcquisitionDate": "2023-08-29T00:00:00Z", "NumberOfShares": "1550.661949", "AcquisitionNumber": "1", "OrigemAmortizacao": "false", "CostValue": "78985.16", "CotaCetipada": "false"}, {"CostPrice": "51.0120347", "IncomeTax": "3844.39", "VirtualIOF": "0.0", "NetAssetValue": "441810.54", "GrossAssetValue": "445654.93", "AcquisitionDate": "2023-09-04T00:00:00Z", "NumberOfShares": "8259.988227", "AcquisitionNumber": "2", "OrigemAmortizacao": "false", "CostValue": "421358.81", "CotaCetipada": "false"}, {"CostPrice": "52.7995938", "IncomeTax": "13312.97", "VirtualIOF": "0.0", "NetAssetValue": "2753355.79", "GrossAssetValue": "2766668.76", "AcquisitionDate": "2023-12-21T00:00:00Z", "NumberOfShares": "51278.803588", "AcquisitionNumber": "3", "OrigemAmortizacao": "false", "CostValue": "2707500.00", "CotaCetipada": "false"}, {"CostPrice": "53.2413365", "IncomeTax": "4514.18", "VirtualIOF": "0.0", "NetAssetValue": "1515548.84", "GrossAssetValue": "1520063.02", "AcquisitionDate": "2024-01-16T00:00:00Z", "NumberOfShares": "28173.597783", "AcquisitionNumber": "4", "OrigemAmortizacao": "false", "CostValue": "1500000.00", "CotaCetipada": "false"}, {"CostPrice": "53.345766", "IncomeTax": "1243.1", "VirtualIOF": "170.87", "NetAssetValue": "504281.81", "GrossAssetValue": "505695.78", "AcquisitionDate": "2024-01-22T00:00:00Z", "NumberOfShares": "9372.81508", "AcquisitionNumber": "5", "OrigemAmortizacao": "false", "CostValue": "500000.00", "CotaCetipada": "false"}], "CotaCetipadaFundoExterno": "false", "PositionDate": "2024-02-20T00:00:00Z", "ProcessingDateTime": "2024-02-21T12:21:11.463Z"}], "InvestmentFundCotaCetipada": [], "Derivative": [{}], "PayableReceivables": [{"Credit": []}], "PendingSettlements": [{"InvestmentFund": []}], "Cash": [{"CashCollateral": [], "CurrentAccount": {"Value": "0.0", "PositionDate": "2024-02-07T00:00:00"}, "CashInvested": []}], "EventCreateDate": "2024-10-09T15:40:09.356"}